.gitignore
MANIFEST.in
README.rst
bootstrap.py
buildout.cfg
setup.py
docs/INSTALL.txt
docs/LICENSE.GPL
docs/LICENSE.txt
zest/__init__.py
zest.cachetuning.egg-info/PKG-INFO
zest.cachetuning.egg-info/SOURCES.txt
zest.cachetuning.egg-info/dependency_links.txt
zest.cachetuning.egg-info/entry_points.txt
zest.cachetuning.egg-info/namespace_packages.txt
zest.cachetuning.egg-info/not-zip-safe
zest.cachetuning.egg-info/requires.txt
zest.cachetuning.egg-info/top_level.txt
zest/cachetuning/HISTORY.txt
zest/cachetuning/__init__.py
zest/cachetuning/config.py
zest/cachetuning/configure.zcml
zest/cachetuning/events.py
zest/cachetuning/tool.py
zest/cachetuning/version.txt
zest/cachetuning/browser/__init__.py
zest/cachetuning/browser/configure.zcml
zest/cachetuning/browser/fullname.py
zest/cachetuning/profiles/default/controlpanel.xml
zest/cachetuning/profiles/default/jsregistry.xml
zest/cachetuning/profiles/default/skins.xml
zest/cachetuning/profiles/default/toolset.xml
zest/cachetuning/profiles/default/types.xml
zest/cachetuning/profiles/default/types/CacheTuningTool.xml
zest/cachetuning/skins/zest_cachetuning/jquery.cookie.js
zest/cachetuning/skins/zest_cachetuning/zest.cachetuning_anon.js.pt
zest/cachetuning/skins/zest_cachetuning/zest.cachetuning_auth.js.pt
zest/cachetuning/tests/__init__.py
zest/cachetuning/tests/base.py
zest/cachetuning/tests/install.txt
zest/cachetuning/tests/js_generation.txt
zest/cachetuning/tests/test_install.py
zest/cachetuning/tests/test_js.py
zest/cachetuning/tests/test_views.py
zest/cachetuning/tests/views.txt