Metadata-Version: 1.0
Name: zest.cachetuning
Version: 0.4
Summary: UNKNOWN
Home-page: http://svn.plone.org/svn/collective/
Author: UNKNOWN
Author-email: UNKNOWN
License: GPL
Platform: UNKNOWN
Classifier: Framework :: Plone
Classifier: Programming Language :: Python
